tifa/__init__.py
tifa/__main__.py
tifa/cli.py
tifa/config.py
tifa/consts.py
tifa/core.py
tifa/errors.py
tifa/file.py
tifa/filters.py
tifa/prompt.py
tifa/utils.py
tifa/validates.py
tifa/validation.py
tifa/templates/.DS_Store
tifa/templates/Pipfile.j2
tifa/templates/__init__.py.j2
tifa/templates/manage.py.j2
tifa/templates/package.json.j2
tifa/templates/readme.md.j2
tifa/templates/requirements.txt.j2
tifa/templates/tifa.example.yaml
tifa/templates/conf/.babelrc.j2
tifa/templates/conf/assets.json.j2
tifa/templates/conf/base_settings.py.j2
tifa/templates/conf/dev_settings.py.j2
tifa/templates/conf/gunicorn_conf.py.j2
tifa/templates/conf/nginx.conf.j2
tifa/templates/conf/supervisor.conf.j2
tifa/templates/conf/webpack.base.js.j2
tifa/templates/conf/webpack.dev.js.j2
tifa/templates/conf/webpack.prod.js.j2
tifa/templates/db/__init__.py.j2
tifa/templates/db/base.py.j2
tifa/templates/db/table.py.j2
tifa/templates/fn/App.vue.j2
tifa/templates/fn/main.js.j2
tifa/templates/fn/normalize.css.j2
tifa/templates/html/base.html.j2
tifa/templates/min/manage.j2
tifa/templates/min/manage.py.j2
tifa/templates/min/requirements.txt
tifa/templates/min/<proj>/.DS_Store
tifa/templates/min/<proj>/__init__.j2
tifa/templates/min/<proj>/__init__.py.j2
tifa/templates/min/<proj>/routes/__init__.j2
tifa/templates/min/<proj>/routes/__init__.py.j2
tifa/templates/min/<proj>/routes/api.j2
tifa/templates/min/<proj>/routes/api.py.j2
tifa/templates/min/<proj>/routes/front.j2
tifa/templates/min/<proj>/routes/front.py.j2
tifa/templates/model/__init__.py.j2
tifa/templates/model/base.py.j2
tifa/templates/model/table.py.j2
tifa/templates/models/__init__.py.j2
tifa/templates/models/base.py.j2
tifa/templates/models/table.py.j2
tifa/templates/routes/__init__.py.j2
tifa/templates/routes/route.py.j2
tifa-0.3.2.dist-info/DESCRIPTION.rst
tifa-0.3.2.dist-info/METADATA
tifa-0.3.2.dist-info/RECORD
tifa-0.3.2.dist-info/WHEEL
tifa-0.3.2.dist-info/entry_points.txt
tifa-0.3.2.dist-info/metadata.json
tifa-0.3.2.dist-info/top_level.txt
