Metadata-Version: 2.0
Name: tifa
Version: 0.3.2
Summary: a modern flask scaffolding
Home-page: https://github.com/wddwycc/tifa
Author: duan
Author-email: wddwyss@gmail.com
License: MIT
Platform: UNKNOWN
Classifier: Development Status :: 4 - Beta
Classifier: Intended Audience :: Developers
Classifier: Intended Audience :: System Administrators
Classifier: License :: OSI Approved :: MIT License
Classifier: Natural Language :: English
Classifier: Programming Language :: Python
Classifier: Programming Language :: Python :: 2.7
Classifier: Programming Language :: Python :: 3.5
Classifier: Programming Language :: Python :: 3.6
Classifier: Topic :: Software Development
Classifier: Topic :: Software Development :: Code Generators
Requires-Dist: click (==6.7)
Requires-Dist: Jinja2 (==2.10)
Requires-Dist: PyYAML (==3.12)
Requires-Dist: voluptuous (==0.11.1)
